restfull/__init__.py
restfull/base_auth.py
restfull/basic_auth.py
restfull/bearer_auth.py
restfull/data.py
restfull/exceptions.py
restfull/no_auth.py
restfull/restapi.py
restfull-1.0.13.dist-info/LICENSE.txt
restfull-1.0.13.dist-info/METADATA
restfull-1.0.13.dist-info/WHEEL
restfull-1.0.13.dist-info/RECORD
