Metadata-Version: 2.1
Name: restfull
Version: 1.0.13
Summary: Python REST API Frontend
Keywords: utilities,rest,api
Author: Michael Minichino
Author-email: info@unix.us.com
Requires-Python: >=3.8,<4
Classifier: Development Status :: 5 - Production/Stable
Classifier: Intended Audience :: Developers
Classifier: License :: OSI Approved :: MIT License
Classifier: Operating System :: OS Independent
Classifier: Programming Language :: Python
Classifier: Programming Language :: Python :: 3
Classifier: Programming Language :: Python :: 3.8
Classifier: Programming Language :: Python :: 3.9
Classifier: Programming Language :: Python :: 3.10
Classifier: Programming Language :: Python :: 3.11
Classifier: Programming Language :: Python :: 3.12
Classifier: Topic :: Database
Classifier: Topic :: Software Development :: Libraries
Classifier: Topic :: Software Development :: Libraries :: Python Modules
Requires-Dist: aiohttp (>=3.9.3)
Requires-Dist: attrs (>=23.1.0)
Requires-Dist: certifi (>=2024.8.30)
Requires-Dist: pytoolbase (>=1.0.2)
Requires-Dist: requests (>=2.31.0)
Project-URL: Homepage, https://github.com/mminichino/restfull
